uniconfig/__init__.py
uniconfig-0.0.1.dist-info/LICENSE
uniconfig-0.0.1.dist-info/METADATA
uniconfig-0.0.1.dist-info/WHEEL
uniconfig-0.0.1.dist-info/top_level.txt
uniconfig-0.0.1.dist-info/RECORD
