Metadata-Version: 2.1
Name: uniconfig
Version: 0.0.1
Summary: Python library for unifying configuration handling
Home-page: https://github.com/kblin/uniconfig
Author: Kai Blin
Author-email: kblin@biosustain.dtu.dk
License: Apache Software License
Platform: POSIX
Classifier: License :: OSI Approved :: Apache Software License
Classifier: Development Status :: 3 - Alpha
Classifier: Programming Language :: Python
Classifier: Programming Language :: Python :: 3
Classifier: Programming Language :: Python :: 3.6
Classifier: Operating System :: POSIX
Classifier: Intended Audience :: Developers
Classifier: Topic :: Software Development
Classifier: Topic :: Software Development :: Libraries
Requires-Dist: toml
Provides-Extra: shipping
Requires-Dist: twine; extra == 'shipping'
Provides-Extra: testing
Requires-Dist: coverage; extra == 'testing'
Requires-Dist: pytest; extra == 'testing'
Requires-Dist: pytest-cov; extra == 'testing'
